faq_rai_sdk/__init__.py
faq_rai_sdk/_client.py
faq_rai_sdk/_configuration.py
faq_rai_sdk/_patch.py
faq_rai_sdk/py.typed
faq_rai_sdk/_utils/__init__.py
faq_rai_sdk/_utils/serialization.py
faq_rai_sdk/aio/__init__.py
faq_rai_sdk/aio/_client.py
faq_rai_sdk/aio/_configuration.py
faq_rai_sdk/aio/_patch.py
faq_rai_sdk/aio/operations/__init__.py
faq_rai_sdk/aio/operations/_operations.py
faq_rai_sdk/aio/operations/_patch.py
faq_rai_sdk/operations/__init__.py
faq_rai_sdk/operations/_operations.py
faq_rai_sdk/operations/_patch.py
faq_rai_sdk-0.1.4.dist-info/licenses/LICENSE
faq_rai_sdk-0.1.4.dist-info/METADATA
faq_rai_sdk-0.1.4.dist-info/WHEEL
faq_rai_sdk-0.1.4.dist-info/top_level.txt
faq_rai_sdk-0.1.4.dist-info/RECORD
