Metadata-Version: 2.4
Name: faq-rai-sdk
Version: 0.1.4
Summary: RAI Package contains a Prompt Reviewer and Updater and test case generator for faster Copilot Development
Home-page: https://github.com/MAQ-Software-Solutions/maqraisdk
Author: Lalit Gour
Author-email: lalitg@maqsoftware.com
Keywords: ai,copilot,prompt,testing,rai,agent
Classifier: Development Status :: 3 - Alpha
Classifier: Intended Audience :: Developers
Classifier: Programming Language :: Python :: 3
Classifier: Programming Language :: Python :: 3.10
Classifier: Programming Language :: Python :: 3.11
Classifier: Programming Language :: Python :: 3.12
Classifier: License :: OSI Approved :: MIT License
Classifier: Operating System :: OS Independent
Classifier: Topic :: Software Development :: Libraries :: Python Modules
Requires-Python: >=3.10,<3.13
License-File: LICENSE
Requires-Dist: crewai[tools]==0.120.1
Requires-Dist: types-PyYAML==6.0.12.20250516
Requires-Dist: PyYAML==6.0.2
Requires-Dist: onnxruntime==1.22.0
Requires-Dist: azure-core>=1.26.0
Requires-Dist: isodate>=0.6.1
Dynamic: author
Dynamic: author-email
Dynamic: classifier
Dynamic: description
Dynamic: description-content-type
Dynamic: home-page
Dynamic: keywords
Dynamic: license-file
Dynamic: requires-dist
Dynamic: requires-python
Dynamic: summary
